pcapmq/__init__.py
pcapmq/cli.py
pcapmq/pcapmq.py
pcapmq-0.1.1.dist-info/METADATA
pcapmq-0.1.1.dist-info/RECORD
pcapmq-0.1.1.dist-info/WHEEL
pcapmq-0.1.1.dist-info/entry_points.txt
pcapmq-0.1.1.dist-info/top_level.txt
