Metadata-Version: 2.1
Name: pcapmq
Version: 0.1.1
Summary: Publish PCAP result to MQTT
Home-page: https://github.com/awarecan/pcapmq
Author: Jason Hu
Author-email: awaregit@gmail.com
License: BSD license
Keywords: pcapmq
Platform: UNKNOWN
Classifier: Development Status :: 2 - Pre-Alpha
Classifier: Intended Audience :: Developers
Classifier: License :: OSI Approved :: BSD License
Classifier: Natural Language :: English
Classifier: Programming Language :: Python :: 3
Classifier: Programming Language :: Python :: 3.5
Classifier: Programming Language :: Python :: 3.6
Requires-Dist: Click (>=6.0)
Requires-Dist: hbmqtt (>=0.9.1)
Requires-Dist: pypcap (>=1.2.1)
Requires-Dist: dpkt (>=1.9.1)
